emojify_python/__init__.py
emojify_python/__main__.py
emojify_python/advanced.py
emojify_python/better_errors.py
emojify_python/cache.py
emojify_python/core.py
emojify_python/debugger.py
emojify_python/enhanced.py
emojify_python/extended_mappings.py
emojify_python/file_support.py
emojify_python/hooks.py
emojify_python/jupyter_magic.py
emojify_python/lazy_loader.py
emojify_python/mappings.py
emojify_python/operator_transformer.py
emojify_python/operators.py
emojify_python/pytest_plugin.py
emojify_python/repl.py
emojify_python/simple_exec.py
emojify_python/transformer.py
emojify_python/utils.py
emojify_python-1.1.1.dist-info/licenses/LICENSE
emojify_python-1.1.1.dist-info/METADATA
emojify_python-1.1.1.dist-info/WHEEL
emojify_python-1.1.1.dist-info/top_level.txt
emojify_python-1.1.1.dist-info/RECORD
