Metadata-Version: 2.4
Name: emojify-python
Version: 1.1.1
Summary: Import Python modules using emojis 🐍
Home-page: https://github.com/arpanghoshal/emojify-python
Author: Arpan Ghoshal
Author-email: Arpan Ghoshal <contact@arpanghoshal.com>
License: MIT
Project-URL: Homepage, https://github.com/arpanghoshal/emojify-python
Project-URL: Documentation, https://github.com/arpanghoshal/emojify-python#readme
Project-URL: Repository, https://github.com/arpanghoshal/emojify-python
Project-URL: Issues, https://github.com/arpanghoshal/emojify-python/issues
Keywords: emoji,import,fun,python,programming,emojify
Classifier: Development Status :: 5 - Production/Stable
Classifier: Intended Audience :: Developers
Classifier: License :: OSI Approved :: MIT License
Classifier: Programming Language :: Python :: 3
Classifier: Programming Language :: Python :: 3.8
Classifier: Programming Language :: Python :: 3.9
Classifier: Programming Language :: Python :: 3.10
Classifier: Programming Language :: Python :: 3.11
Classifier: Programming Language :: Python :: 3.12
Classifier: Programming Language :: Python :: 3.13
Classifier: Topic :: Software Development :: Libraries :: Python Modules
Classifier: Topic :: Utilities
Requires-Python: >=3.8
License-File: LICENSE
Dynamic: author
Dynamic: home-page
Dynamic: license-file
Dynamic: requires-python
